face_vet/__init__.py
face_vet/core.py
face_vet/crop_face.py
face_vet/eye_nose_distance_detection.py
face_vet/face_detection.py
face_vet/image_quality_check.py
face_vet/text_extraction.py
face_vet/models/haarcascade_frontalface_alt2.xml
face_vet/models/haarcascade_frontalface_default.xml
face_vet/models/shape_predictor_68_face_landmarks.dat
face_vet-1.2.0.dist-info/METADATA
face_vet-1.2.0.dist-info/WHEEL
face_vet-1.2.0.dist-info/top_level.txt
face_vet-1.2.0.dist-info/RECORD
