Metadata-Version: 2.4
Name: face-vet
Version: 1.2.0
Summary: A package to detect fake or low-quality images using OpenCV and Tesseract
Author: Vinayak Gaikwad
Author-email: vinayak.gaikwad@fdplfinance.com
Classifier: Programming Language :: Python :: 3
Classifier: Operating System :: OS Independent
Requires-Python: >=3.6
Requires-Dist: opencv-python
Requires-Dist: pytesseract
Requires-Dist: numpy
Requires-Dist: Pillow
Requires-Dist: setuptools
Requires-Dist: dlib
Dynamic: author
Dynamic: author-email
Dynamic: classifier
Dynamic: description
Dynamic: description-content-type
Dynamic: requires-dist
Dynamic: requires-python
Dynamic: summary
